{"stats":{"minecraft:picked_up":{"minecraft:wheat":17,"minecraft:light_blue_concrete":1,"minecraft:purple_wool":1,"minecraft:anvil":6,"minecraft:potato":42,"minecraft:oak_log":1,"minecraft:item_frame":6,"minecraft:blue_orchid":1,"minecraft:apple":1,"minecraft:wheat_seeds":43,"minecraft:yellow_stained_glass":2,"minecraft:beef":2,"minecraft:player_head":1,"minecraft:sugar_cane":3,"minecraft:purple_concrete":1,"minecraft:stick":1,"minecraft:daylight_detector":11,"minecraft:carrot":44,"minecraft:green_carpet":2,"minecraft:shulker_box":5,"minecraft:netherite_block":315,"minecraft:light_blue_wool":1,"minecraft:white_terracotta":7,"minecraft:oak_sapling":2},"minecraft:custom":{"minecraft:open_shulker_box":1,"minecraft:leave_game":68,"minecraft:time_since_death":2106300,"minecraft:time_since_rest":2106300,"minecraft:sprint_one_cm":68641,"minecraft:damage_taken":70,"minecraft:walk_one_cm":83415,"minecraft:drop":22,"minecraft:swim_one_cm":325,"minecraft:fly_one_cm":237037,"minecraft:open_chest":17,"minecraft:crouch_one_cm":22225,"minecraft:play_time":2106300,"minecraft:sneak_time":14119,"minecraft:walk_under_water_one_cm":52,"minecraft:jump":618,"minecraft:walk_on_water_one_cm":1256,"minecraft:total_world_time":2106300,"minecraft:fall_one_cm":64967},"minecraft:used":{"minecraft:oak_fence":1,"minecraft:wheat_seeds":16,"minecraft:water_bucket":1,"minecraft:diorite":13,"minecraft:red_concrete":1,"minecraft:dispenser":1,"minecraft:purple_glazed_terracotta":1,"minecraft:stone":467,"minecraft:sugar_cane":3,"minecraft:player_head":1,"minecraft:large_amethyst_bud":3,"minecraft:oak_leaves":71,"minecraft:spruce_leaves":50,"minecraft:dirt":1,"minecraft:spyglass":4,"minecraft:vine":7,"minecraft:light_blue_concrete":1,"minecraft:crafting_table":1,"minecraft:light_blue_wool":1,"minecraft:carrot":13,"minecraft:shulker_box":1,"minecraft:tuff":6,"minecraft:glow_lichen":17,"minecraft:piglin_head":1,"minecraft:small_amethyst_bud":4,"minecraft:oak_log":23,"minecraft:amethyst_cluster":7,"minecraft:daylight_detector":11,"minecraft:red_wool":1,"minecraft:yellow_stained_glass":4,"minecraft:lantern":7,"minecraft:grass_block":100,"minecraft:blue_orchid":1,"minecraft:stone_button":4,"minecraft:spruce_trapdoor":17,"minecraft:deepslate":7,"minecraft:gravel":2,"minecraft:bedrock":25,"minecraft:green_carpet":1,"minecraft:deepslate_diamond_ore":1,"minecraft:purple_concrete":1,"minecraft:sweet_berries":4,"minecraft:medium_amethyst_bud":4,"minecraft:andesite":20,"minecraft:chain":22,"minecraft:polished_blackstone_button":12,"minecraft:potato":12,"minecraft:bone_meal":93,"minecraft:purple_wool":1,"minecraft:lime_glazed_terracotta":1,"minecraft:experience_bottle":37,"minecraft:pointed_dripstone":19},"minecraft:mined":{"minecraft:spruce_leaves":5,"minecraft:carrots":12,"minecraft:wheat":17,"minecraft:oak_log":1,"minecraft:potatoes":12,"minecraft:oak_leaves":8},"minecraft:dropped":{"minecraft:enchanted_book":1,"minecraft:daylight_detector":11,"minecraft:spyglass":1,"minecraft:wheat_seeds":1,"minecraft:player_head":75,"minecraft:allay_spawn_egg":1,"minecraft:wheat":64,"minecraft:experience_bottle":185,"minecraft:shulker_box":1,"minecraft:carrot":64,"minecraft:stick":1,"minecraft:iron_block":1,"minecraft:potato":64,"minecraft:beef":2}},"DataVersion":3463}